exe_index/__init__.py
exe_index/exe_index.py
exe_index-0.0.3.dist-info/METADATA
exe_index-0.0.3.dist-info/WHEEL
exe_index-0.0.3.dist-info/entry_points.txt
exe_index-0.0.3.dist-info/top_level.txt
exe_index-0.0.3.dist-info/RECORD
