Metadata-Version: 2.1
Name: exe-index
Version: 0.0.3
Summary: A Python package.
Requires-Dist: click ~=8.1.7
Requires-Dist: packaging ~=24.1
